{
  "verification_timestamp": "2025-07-02T10:14:32.341836",
  "overall_status": "PASSED",
  "overall_score": "39/39",
  "step_results": {
    "step_2_1a": true,
    "step_2_1b": true,
    "step_2_2a": true,
    "step_2_2b": true,
    "output_files": true
  },
  "detailed_test_results": {
    "step_2_1a": {
      "average_regime_length": true,
      "decade_transitions": true,
      "stability_metrics": true,
      "transition_matrices": true,
      "seasonal_patterns": true,
      "summary_statistics": true,
      "expected_frequencies": "True"
    },
    "step_2_1b": {
      "gdp_analysis": true,
      "inflation_analysis": true,
      "yield_curve_analysis": true,
      "employment_analysis": true,
      "validation_report": true,
      "cross_regime_comparisons": true,
      "vix_analysis": true
    },
    "step_2_2a": {
      "absolute_returns": true,
      "risk_adjusted_returns": true,
      "tail_risk_analysis": true,
      "consistency_metrics": true,
      "all_factors_covered": true,
      "annualized_metrics": true,
      "goldilocks_best_performance": true,
      "recession_defensive_quality": true
    },
    "step_2_2b": {
      "anova_tests": true,
      "pairwise_ttests": true,
      "bootstrap_confidence": true,
      "transition_impact": true,
      "significance_documentation": true,
      "significance_indicators": true,
      "correct_transition_count": true
    },
    "output_files": {
      "phase2_regime_analysis.json_exists": true,
      "phase2_regime_analysis.json_valid_json": true,
      "phase2_regime_analysis.json_has_content": true,
      "phase2_performance_analysis.json_exists": true,
      "phase2_performance_analysis.json_valid_json": true,
      "phase2_performance_analysis.json_has_content": true,
      "phase2_complete_summary.json_exists": true,
      "phase2_complete_summary.json_valid_json": true,
      "phase2_complete_summary.json_has_content": true,
      "phase2_execution_success": true
    }
  },
  "roadmap_compliance": {
    "step_2_1a_requirements": 7,
    "step_2_1b_requirements": 7,
    "step_2_2a_requirements": 8,
    "step_2_2b_requirements": 7,
    "total_requirements": 29
  }
}